hordelib/__init__.py
hordelib/__pyinstaller.py
hordelib/_version.py
hordelib/benchmark.py
hordelib/comfy_horde.py
hordelib/config_path.py
hordelib/consts.py
hordelib/exceptions.py
hordelib/horde.py
hordelib/initialisation.py
hordelib/install_comfy.py
hordelib/preload.py
hordelib/py.typed
hordelib/safety.py
hordelib/safety_checker.py
hordelib/settings.py
hordelib/shared_model_manager.py
hordelib/train.py
hordelib/_comfyui/.gitignore
hordelib/_comfyui/CODEOWNERS
hordelib/_comfyui/LICENSE
hordelib/_comfyui/README.md
hordelib/_comfyui/comfyui_screenshot.png
hordelib/_comfyui/cuda_malloc.py
hordelib/_comfyui/execution.py
hordelib/_comfyui/extra_model_paths.yaml
hordelib/_comfyui/extra_model_paths.yaml.example
hordelib/_comfyui/folder_paths.py
hordelib/_comfyui/latent_preview.py
hordelib/_comfyui/main.py
hordelib/_comfyui/new_updater.py
hordelib/_comfyui/nodes.py
hordelib/_comfyui/pytest.ini
hordelib/_comfyui/requirements.txt
hordelib/_comfyui/server.py
hordelib/_comfyui/app/app_settings.py
hordelib/_comfyui/app/user_manager.py
hordelib/_comfyui/comfy/checkpoint_pickle.py
hordelib/_comfyui/comfy/cli_args.py
hordelib/_comfyui/comfy/clip_config_bigg.json
hordelib/_comfyui/comfy/clip_model.py
hordelib/_comfyui/comfy/clip_vision.py
hordelib/_comfyui/comfy/clip_vision_config_g.json
hordelib/_comfyui/comfy/clip_vision_config_h.json
hordelib/_comfyui/comfy/clip_vision_config_vitl.json
hordelib/_comfyui/comfy/conds.py
hordelib/_comfyui/comfy/controlnet.py
hordelib/_comfyui/comfy/diffusers_convert.py
hordelib/_comfyui/comfy/diffusers_load.py
hordelib/_comfyui/comfy/gligen.py
hordelib/_comfyui/comfy/latent_formats.py
hordelib/_comfyui/comfy/lora.py
hordelib/_comfyui/comfy/model_base.py
hordelib/_comfyui/comfy/model_detection.py
hordelib/_comfyui/comfy/model_management.py
hordelib/_comfyui/comfy/model_patcher.py
hordelib/_comfyui/comfy/model_sampling.py
hordelib/_comfyui/comfy/ops.py
hordelib/_comfyui/comfy/options.py
hordelib/_comfyui/comfy/sample.py
hordelib-2.8.1.dist-info/CHANGELOG.md
hordelib-2.8.1.dist-info/LICENSE
hordelib-2.8.1.dist-info/METADATA
hordelib-2.8.1.dist-info/WHEEL
hordelib-2.8.1.dist-info/entry_points.txt
hordelib-2.8.1.dist-info/top_level.txt
hordelib-2.8.1.dist-info/RECORD
