Metadata-Version: 2.1
Name: hordelib
Version: 2.8.1
Summary: A thin wrapper around ComfyUI to allow use by AI Horde.
Author-email: Jug <jugdev@proton.me>, db0 <mail@dbzer0.com>, tazlin <tazlin.on.github@gmail.com>
License: GNU AFFERO GENERAL PUBLIC LICENSE
Project-URL: Homepage, https://github.com/jug-dev/hordelib
Project-URL: Bug Tracker, https://github.com/jug-dev/hordelib/issues
Project-URL: Changelog, https://github.com/jug-dev/hordelib/blob/releases/CHANGELOG.md
Classifier: Programming Language :: Python :: 3
Classifier: License :: OSI Approved :: GNU Affero General Public License v3
Classifier: Operating System :: OS Independent
Classifier: Development Status :: 2 - Pre-Alpha
Requires-Python: >=3.10
License-File: LICENSE
License-File: CHANGELOG.md
Requires-Dist: horde-sdk >=0.9.1
Requires-Dist: horde-model-reference >=0.5.2
Requires-Dist: pydantic
Requires-Dist: torch >=2.1.0
Requires-Dist: torchvision
Requires-Dist: torchdiffeq
Requires-Dist: torchsde
Requires-Dist: einops
Requires-Dist: open-clip-torch
Requires-Dist: transformers >=4.25.1
Requires-Dist: safetensors >=0.3.0
Requires-Dist: pytorch-lightning
Requires-Dist: pynvml
Requires-Dist: aiohttp
Requires-Dist: accelerate
Requires-Dist: pyyaml
Requires-Dist: pillow
Requires-Dist: loguru
Requires-Dist: GitPython
Requires-Dist: clip-anytorch
Requires-Dist: diffusers
Requires-Dist: omegaconf
Requires-Dist: psutil
Requires-Dist: typing-extensions
Requires-Dist: distro
Requires-Dist: python-dotenv
Requires-Dist: strenum
Requires-Dist: rembg
Requires-Dist: opencv-python
Requires-Dist: opencv-contrib-python
Requires-Dist: timm ==0.9.16
Requires-Dist: scipy
Requires-Dist: addict
Requires-Dist: fairscale
Requires-Dist: scikit-image
Requires-Dist: mediapipe >=0.9.1.0
Requires-Dist: unidecode
Requires-Dist: fuzzywuzzy
Requires-Dist: kornia
